{
  "updated_at": "2026-06-29T11:22:03.100318+00:00",
  "total_scanned": 500,
  "historical_unique_scanned": 472,
  "total_working": 84,
  "total_dead": 416,
  "success_rate": 16.8,
  "top_nodes": [
    {
      "rank": 1,
      "score": 203.5,
      "latency_ms": 81,
      "speed_kbps": 2643.6,
      "country": "US",
      "host": "112.121.***. ***",
      "sni": "videos.apple.com",
      "age_days": 12,
      "uptime": 100.0
    },
    {
      "rank": 2,
      "score": 179.6,
      "latency_ms": 79,
      "speed_kbps": 2870.8,
      "country": "US",
      "host": "38.244.***. ***",
      "sni": "www.apple.com",
      "age_days": 0,
      "uptime": 100.0
    },
    {
      "rank": 3,
      "score": 159.3,
      "latency_ms": 110,
      "speed_kbps": 2151.4,
      "country": "US",
      "host": "38.244.***. ***",
      "sni": "www.apple.com",
      "age_days": 1,
      "uptime": 100.0
    },
    {
      "rank": 4,
      "score": 130.2,
      "latency_ms": 155,
      "speed_kbps": 2504.8,
      "country": "US",
      "host": "38.244.***. ***",
      "sni": "www.apple.com",
      "age_days": 0,
      "uptime": 100.0
    },
    {
      "rank": 5,
      "score": 112.9,
      "latency_ms": 226,
      "speed_kbps": 828.3,
      "country": "US",
      "host": "192.3.***. ***",
      "sni": "apple.com",
      "age_days": 12,
      "uptime": 96.6
    },
    {
      "rank": 6,
      "score": 102.6,
      "latency_ms": 280,
      "speed_kbps": 744.3,
      "country": "US",
      "host": "47.253.***. ***",
      "sni": "www.cloudflare.com",
      "age_days": 12,
      "uptime": 99.5
    },
    {
      "rank": 7,
      "score": 84.1,
      "latency_ms": 314,
      "speed_kbps": 624.0,
      "country": "US",
      "host": "137.184.***. ***",
      "sni": "www.cloudflare.com",
      "age_days": 12,
      "uptime": 87.6
    },
    {
      "rank": 8,
      "score": 82.0,
      "latency_ms": 219,
      "speed_kbps": 1171.0,
      "country": "US",
      "host": "20.84.***. ***",
      "sni": "www.cloudflare.com",
      "age_days": 1,
      "uptime": 64.2
    },
    {
      "rank": 9,
      "score": 78.7,
      "latency_ms": 442,
      "speed_kbps": 520.9,
      "country": "JP",
      "host": "96.62.***. ***",
      "sni": "www.google.com",
      "age_days": 12,
      "uptime": 100.0
    },
    {
      "rank": 10,
      "score": 74.9,
      "latency_ms": 455,
      "speed_kbps": 482.7,
      "country": "JP",
      "host": "13.231.***. ***",
      "sni": "www.yahoo.com",
      "age_days": 12,
      "uptime": 100.0
    },
    {
      "rank": 11,
      "score": 73.0,
      "latency_ms": 338,
      "speed_kbps": 691.0,
      "country": "US",
      "host": "159.89.***. ***",
      "sni": "aws.amazon.com",
      "age_days": 12,
      "uptime": 74.1
    },
    {
      "rank": 12,
      "score": 72.2,
      "latency_ms": 480,
      "speed_kbps": 452.5,
      "country": "JP",
      "host": "138.2.***. ***",
      "sni": "www.icloud.com",
      "age_days": 12,
      "uptime": 98.0
    },
    {
      "rank": 13,
      "score": 66.4,
      "latency_ms": 329,
      "speed_kbps": 134.4,
      "country": "CA",
      "host": "130.107.***. ***",
      "sni": "google.com",
      "age_days": 12,
      "uptime": 99.0
    },
    {
      "rank": 14,
      "score": 64.0,
      "latency_ms": 611,
      "speed_kbps": 353.1,
      "country": "HK",
      "host": "64.49.***. ***",
      "sni": "www.apple.com",
      "age_days": 12,
      "uptime": 100.0
    },
    {
      "rank": 15,
      "score": 60.0,
      "latency_ms": 475,
      "speed_kbps": 332.1,
      "country": "JP",
      "host": "103.76.***. ***",
      "sni": "www.apple.com",
      "age_days": 1,
      "uptime": 100.0
    },
    {
      "rank": 16,
      "score": 59.6,
      "latency_ms": 687,
      "speed_kbps": 301.7,
      "country": "FR",
      "host": "194.164.***. ***",
      "sni": "www.samsung.com",
      "age_days": 12,
      "uptime": 100.0
    },
    {
      "rank": 17,
      "score": 59.5,
      "latency_ms": 873,
      "speed_kbps": 361.2,
      "country": "TR",
      "host": "141.98.***. ***",
      "sni": "www.google.com",
      "age_days": 12,
      "uptime": 100.0
    },
    {
      "rank": 18,
      "score": 59.2,
      "latency_ms": 700,
      "speed_kbps": 316.7,
      "country": "NL",
      "host": "138.124.***. ***",
      "sni": "www.google.com",
      "age_days": 12,
      "uptime": 98.5
    },
    {
      "rank": 19,
      "score": 58.6,
      "latency_ms": 631,
      "speed_kbps": 323.4,
      "country": "US",
      "host": "31.76.***. ***",
      "sni": "icloud.com",
      "age_days": 12,
      "uptime": 94.5
    },
    {
      "rank": 20,
      "score": 57.4,
      "latency_ms": 934,
      "speed_kbps": 358.4,
      "country": "TR",
      "host": "37.221.***. ***",
      "sni": "www.yahoo.com",
      "age_days": 12,
      "uptime": 98.0
    },
    {
      "rank": 21,
      "score": 56.7,
      "latency_ms": 842,
      "speed_kbps": 297.2,
      "country": "FR",
      "host": "51.44.***. ***",
      "sni": "yahoo.com",
      "age_days": 12,
      "uptime": 100.0
    },
    {
      "rank": 22,
      "score": 56.3,
      "latency_ms": 780,
      "speed_kbps": 270.3,
      "country": "SE",
      "host": "144.31.***. ***",
      "sni": "www.twitch.tv",
      "age_days": 12,
      "uptime": 100.0
    },
    {
      "rank": 23,
      "score": 55.9,
      "latency_ms": 903,
      "speed_kbps": 297.4,
      "country": "FR",
      "host": "51.44.***. ***",
      "sni": "yahoo.com",
      "age_days": 12,
      "uptime": 100.0
    },
    {
      "rank": 24,
      "score": 55.0,
      "latency_ms": 882,
      "speed_kbps": 294.1,
      "country": "NL",
      "host": "89.124.***. ***",
      "sni": "tv.apple.com",
      "age_days": 12,
      "uptime": 99.0
    },
    {
      "rank": 25,
      "score": 55.0,
      "latency_ms": 847,
      "speed_kbps": 263.6,
      "country": "TR",
      "host": "185.181.***. ***",
      "sni": "gateway.icloud.com",
      "age_days": 12,
      "uptime": 100.0
    },
    {
      "rank": 26,
      "score": 54.5,
      "latency_ms": 884,
      "speed_kbps": 262.9,
      "country": "TR",
      "host": "185.181.***. ***",
      "sni": "gateway.icloud.com",
      "age_days": 12,
      "uptime": 100.0
    },
    {
      "rank": 27,
      "score": 54.2,
      "latency_ms": 883,
      "speed_kbps": 264.4,
      "country": "TR",
      "host": "185.181.***. ***",
      "sni": "gateway.icloud.com",
      "age_days": 12,
      "uptime": 99.5
    },
    {
      "rank": 28,
      "score": 53.8,
      "latency_ms": 969,
      "speed_kbps": 269.2,
      "country": "HK",
      "host": "103.166.***. ***",
      "sni": "www.samsung.com",
      "age_days": 12,
      "uptime": 100.0
    },
    {
      "rank": 29,
      "score": 53.7,
      "latency_ms": 356,
      "speed_kbps": 361.8,
      "country": "US",
      "host": "156.229.***. ***",
      "sni": "www.icloud.com",
      "age_days": 12,
      "uptime": 76.8
    },
    {
      "rank": 30,
      "score": 53.6,
      "latency_ms": 923,
      "speed_kbps": 260.3,
      "country": "TR",
      "host": "185.181.***. ***",
      "sni": "gateway.icloud.com",
      "age_days": 12,
      "uptime": 99.5
    },
    {
      "rank": 31,
      "score": 53.2,
      "latency_ms": 834,
      "speed_kbps": 264.3,
      "country": "RS",
      "host": "185.48.***. ***",
      "sni": "www.samsung.com",
      "age_days": 12,
      "uptime": 96.5
    },
    {
      "rank": 32,
      "score": 53.1,
      "latency_ms": 1061,
      "speed_kbps": 273.8,
      "country": "IT",
      "host": "204.216.***. ***",
      "sni": "yahoo.com",
      "age_days": 12,
      "uptime": 100.0
    },
    {
      "rank": 33,
      "score": 53.0,
      "latency_ms": 604,
      "speed_kbps": 377.9,
      "country": "GB",
      "host": "20.0.***. ***",
      "sni": "www.cloudflare.com",
      "age_days": 12,
      "uptime": 87.9
    },
    {
      "rank": 34,
      "score": 52.9,
      "latency_ms": 969,
      "speed_kbps": 259.0,
      "country": "LV",
      "host": "95.182.***. ***",
      "sni": "yahoo.com",
      "age_days": 12,
      "uptime": 99.4
    },
    {
      "rank": 35,
      "score": 52.7,
      "latency_ms": 852,
      "speed_kbps": 225.7,
      "country": "GB",
      "host": "51.89.***. ***",
      "sni": "www.samsung.com",
      "age_days": 12,
      "uptime": 99.5
    },
    {
      "rank": 36,
      "score": 51.3,
      "latency_ms": 860,
      "speed_kbps": 266.5,
      "country": "CH",
      "host": "83.228.***. ***",
      "sni": "www.yahoo.com",
      "age_days": 2,
      "uptime": 100.0
    },
    {
      "rank": 37,
      "score": 50.9,
      "latency_ms": 682,
      "speed_kbps": 334.4,
      "country": "IT",
      "host": "72.146.***. ***",
      "sni": "www.cloudflare.com",
      "age_days": 1,
      "uptime": 100.0
    },
    {
      "rank": 38,
      "score": 50.7,
      "latency_ms": 725,
      "speed_kbps": 144.6,
      "country": "GB",
      "host": "149.248.***. ***",
      "sni": "aws.amazon.com",
      "age_days": 12,
      "uptime": 99.5
    },
    {
      "rank": 39,
      "score": 50.1,
      "latency_ms": 2098,
      "speed_kbps": 306.1,
      "country": "DE",
      "host": "83.243.***. ***",
      "sni": "www.cloudflare.com",
      "age_days": 12,
      "uptime": 100.0
    },
    {
      "rank": 40,
      "score": 49.8,
      "latency_ms": 690,
      "speed_kbps": 321.6,
      "country": "DE",
      "host": "91.107.***. ***",
      "sni": "play.google.com",
      "age_days": 12,
      "uptime": 89.0
    },
    {
      "rank": 41,
      "score": 49.7,
      "latency_ms": 1720,
      "speed_kbps": 335.2,
      "country": "NL",
      "host": "89.23.***. ***",
      "sni": "www.samsung.com",
      "age_days": 12,
      "uptime": 94.7
    },
    {
      "rank": 42,
      "score": 47.0,
      "latency_ms": 812,
      "speed_kbps": 312.7,
      "country": "FR",
      "host": "147.135.***. ***",
      "sni": "api.github.com",
      "age_days": 1,
      "uptime": 92.9
    },
    {
      "rank": 43,
      "score": 46.6,
      "latency_ms": 1356,
      "speed_kbps": 191.0,
      "country": "KZ",
      "host": "178.236.***. ***",
      "sni": "google.com",
      "age_days": 12,
      "uptime": 99.4
    },
    {
      "rank": 44,
      "score": 45.7,
      "latency_ms": 1544,
      "speed_kbps": 183.9,
      "country": "??",
      "host": "raff-vpn-kz***",
      "sni": "google.com",
      "age_days": 12,
      "uptime": 100.0
    },
    {
      "rank": 45,
      "score": 44.5,
      "latency_ms": 2982,
      "speed_kbps": 270.1,
      "country": "FR",
      "host": "194.226.***. ***",
      "sni": "yahoo.com",
      "age_days": 12,
      "uptime": 95.4
    },
    {
      "rank": 46,
      "score": 44.4,
      "latency_ms": 1022,
      "speed_kbps": 303.9,
      "country": "??",
      "host": "fr-d.duckray.***. ***",
      "sni": "api.github.com",
      "age_days": 2,
      "uptime": 92.1
    },
    {
      "rank": 47,
      "score": 44.1,
      "latency_ms": 711,
      "speed_kbps": null,
      "country": "FR",
      "host": "5.196.***. ***",
      "sni": "dash.cloudflare.com",
      "age_days": 12,
      "uptime": 100.0
    },
    {
      "rank": 48,
      "score": 43.3,
      "latency_ms": 678,
      "speed_kbps": null,
      "country": "??",
      "host": "de.ko.pro***",
      "sni": "google.com",
      "age_days": 12,
      "uptime": 97.6
    },
    {
      "rank": 49,
      "score": 42.3,
      "latency_ms": 714,
      "speed_kbps": null,
      "country": "DE",
      "host": "23.26.***. ***",
      "sni": "google.com",
      "age_days": 12,
      "uptime": 97.1
    },
    {
      "rank": 50,
      "score": 41.7,
      "latency_ms": 926,
      "speed_kbps": 177.1,
      "country": "LV",
      "host": "37.233.***. ***",
      "sni": "yahoo.com",
      "age_days": 12,
      "uptime": 86.1
    }
  ],
  "country_distribution": {
    "US": 1906,
    "??": 1474,
    "HK": 748,
    "DE": 499,
    "SG": 415,
    "NL": 282,
    "KR": 279,
    "FR": 135,
    "FI": 135,
    "RU": 114,
    "TR": 98,
    "GB": 96,
    "SE": 59,
    "JP": 56,
    "CH": 53,
    "PL": 50,
    "CA": 44,
    "IR": 43,
    "IT": 37,
    "LV": 31,
    "KZ": 21,
    "AT": 19,
    "CZ": 16,
    "GE": 16,
    "EE": 15,
    "AE": 13,
    "AU": 12,
    "IE": 10,
    "IN": 10,
    "AL": 8,
    "NO": 7,
    "ES": 7,
    "MD": 7,
    "BG": 7,
    "RS": 6,
    "DK": 6,
    "LU": 5,
    "GR": 4,
    "PK": 3,
    "LT": 3,
    "RO": 3,
    "AM": 2,
    "HU": 2,
    "CN": 2,
    "SA": 2,
    "TW": 2,
    "ZA": 2,
    "VN": 2,
    "IL": 2,
    "CY": 1,
    "QA": 1,
    "BR": 1,
    "BE": 1,
    "PA": 1,
    "KG": 1,
    "LY": 1,
    "IS": 1,
    "CO": 1,
    "PH": 1,
    "LI": 1,
    "AR": 1,
    "UA": 1
  },
  "scan_config": {
    "repos_scanned": 7,
    "files_found": 84,
    "raw_configs": 676847,
    "unique_valid": 6781,
    "max_concurrency": 20,
    "top_n": 50
  }
}